sigevents_us/__init__.py
sigevents_us/events.py
sigevents_US-0.1.dist-info/METADATA
sigevents_US-0.1.dist-info/WHEEL
sigevents_US-0.1.dist-info/top_level.txt
sigevents_US-0.1.dist-info/RECORD
